{
  "build": "pyh5ded981_2",
  "build_number": 2,
  "channel": "https://conda.anaconda.org/conda-forge/noarch",
  "constrains": [
    "python >=3.11"
  ],
  "depends": [
    "python >=3.11",
    "python"
  ],
  "extracted_package_dir": "/Users/macos/anaconda3/pkgs/backports.asyncio.runner-1.2.0-pyh5ded981_2",
  "features": "",
  "files": [],
  "fn": "backports.asyncio.runner-1.2.0-pyh5ded981_2.conda",
  "license": "PSF-2.0",
  "license_family": "PSF",
  "link": {
    "source": "/Users/macos/anaconda3/pkgs/backports.asyncio.runner-1.2.0-pyh5ded981_2",
    "type": 1
  },
  "md5": "0fd7e45c862b3305226a992f9f7b204a",
  "name": "backports.asyncio.runner",
  "noarch": "python",
  "package_tarball_full_path": "/Users/macos/anaconda3/pkgs/backports.asyncio.runner-1.2.0-pyh5ded981_2.conda",
  "package_type": "noarch_python",
  "paths_data": {
    "paths": [],
    "paths_version": 1
  },
  "requested_spec": "None",
  "sha256": "2ade43752e8494f110a2cfb9e4d5b1ea29e3dcb037fba63395442d00371e8bf9",
  "size": 10186,
  "subdir": "noarch",
  "timestamp": 1753456386827,
  "track_features": "",
  "url": "https://conda.anaconda.org/conda-forge/noarch/backports.asyncio.runner-1.2.0-pyh5ded981_2.conda",
  "version": "1.2.0"
}